HISTORY.txt
MANIFEST.in
README.rst
setup.py
rt/__init__.py
rt.simpleslider.egg-info/PKG-INFO
rt.simpleslider.egg-info/SOURCES.txt
rt.simpleslider.egg-info/dependency_links.txt
rt.simpleslider.egg-info/entry_points.txt
rt.simpleslider.egg-info/namespace_packages.txt
rt.simpleslider.egg-info/not-zip-safe
rt.simpleslider.egg-info/requires.txt
rt.simpleslider.egg-info/top_level.txt
rt/simpleslider/__init__.py
rt/simpleslider/configure.zcml
rt/simpleslider/extender.py
rt/simpleslider/interfaces.py
rt/simpleslider/skins.zcml
rt/simpleslider/vocabularies.py
rt/simpleslider/browser/__init__.py
rt/simpleslider/browser/configure.zcml
rt/simpleslider/browser/controlpanel.py
rt/simpleslider/browser/leadimagesource.py
rt/simpleslider/browser/slider_viewlet.pt
rt/simpleslider/browser/slidersource.py
rt/simpleslider/browser/smartlink.py
rt/simpleslider/browser/utils.py
rt/simpleslider/browser/viewlets.py
rt/simpleslider/locales/rt.simpleslider.pot
rt/simpleslider/profiles/default/browserlayer.xml
rt/simpleslider/profiles/default/controlpanel.xml
rt/simpleslider/profiles/default/cssregistry.xml
rt/simpleslider/profiles/default/jsregistry.xml
rt/simpleslider/profiles/default/metadata.xml
rt/simpleslider/profiles/default/propertiestool.xml
rt/simpleslider/profiles/default/registry.xml
rt/simpleslider/profiles/default/skins.xml
rt/simpleslider/skins/simpleslider_resources/bjqs-1.3.js
rt/simpleslider/skins/simpleslider_resources/bjqs.css
rt/simpleslider/skins/simpleslider_resources/wrench.png