Metadata-Version: 1.1
Name: rt.simpleslider
Version: 1.3.4
Summary: A really simple Plone slider based on basic-slider.com
Home-page: http://www.redturtle.it
Author: RedTurtle team
Author-email: svilplone@redturtle.it
License: GPL
Keywords: plone slider
Platform: UNKNOWN
Classifier: Development Status :: 5 - Production/Stable
Classifier: Framework :: Plone
Classifier: Framework :: Plone :: 4.2
Classifier: Framework :: Plone :: Addon
Classifier: License :: OSI Approved :: GNU General Public License (GPL)
Classifier: Programming Language :: Python :: 2.6
Classifier: Programming Language :: Python :: 2.7
